<?xml version="1.0" encoding="utf-8"?><index><!-- saved from url=(0016)http://localhost -->
<stem n="two"><phr n="two"><ent r="7" t="2" w="229" /><ent r="7" t="2" w="229" /><ent r="7" t="5" w="916" /><ent r="7" t="5" w="936" /><ent r="7" t="5" w="936" /><ent r="8" t="5" w="2376" /><ent r="8" t="8" w="7157" /><ent r="8" t="8" w="7157" /><ent r="8" t="8" w="7255" /><ent r="8" t="8" w="7255" /><ent r="7" t="8" w="7762" /><ent r="7" t="8" w="7762" /><ent r="8" t="8" w="8014" /><ent r="8" t="8" w="8014" /><ent r="8" t="8" w="8153" /><ent r="8" t="8" w="8153" /><ent r="7" t="8" w="8424" /><ent r="7" t="8" w="8424" /><ent r="7" t="8" w="9113" /><ent r="7" t="8" w="9113" /><ent r="7" t="8" w="10016" /><ent r="7" t="8" w="10016" /><ent r="7" t="9" w="1907" /><ent r="7" t="9" w="1907" /><ent r="7" t="9" w="3898" /><ent r="7" t="9" w="3898" /><ent r="7" t="9" w="3902" /><ent r="7" t="9" w="3902" /><ent r="7" t="9" w="5483" /><ent r="7" t="9" w="5483" /><ent r="8" t="9" w="7268" /><ent r="8" t="9" w="7268" /><ent r="7" t="9" w="7307" /><ent r="7" t="9" w="7307" /><ent r="7" t="9" w="7713" /><ent r="7" t="9" w="7713" /><ent r="7" t="10" w="1539" /><ent r="7" t="10" w="1539" /><ent r="7" t="10" w="4696" /><ent r="7" t="10" w="4696" /><ent r="7" t="10" w="5835" /><ent r="7" t="10" w="5835" /><ent r="7" t="10" w="6024" /><ent r="7" t="10" w="6024" /><ent r="7" t="10" w="7307" /><ent r="7" t="10" w="7307" /><ent r="7" t="10" w="7448" /><ent r="7" t="10" w="7448" /><ent r="7" t="10" w="7467" /><ent r="7" t="10" w="7467" /><ent r="8" t="10" w="8257" /><ent r="8" t="10" w="8257" /><ent r="7" t="10" w="9890" /><ent r="7" t="10" w="9890" /><ent r="7" t="12" w="781" /><ent r="7" t="12" w="781" /><ent r="7" t="12" w="1504" /><ent r="7" t="12" w="1504" /><ent r="7" t="12" w="1639" /><ent r="7" t="12" w="1639" /><ent r="7" t="12" w="1805" /><ent r="7" t="12" w="1805" /><ent r="7" t="12" w="1992" /><ent r="7" t="12" w="1992" /><ent r="7" t="12" w="2045" /><ent r="7" t="12" w="2045" /><ent r="8" t="12" w="2133" /><ent r="8" t="12" w="2133" /><ent r="7" t="12" w="2295" /><ent r="7" t="12" w="2295" /><ent r="7" t="12" w="3460" /><ent r="7" t="12" w="3460" /><ent r="7" t="12" w="3554" /><ent r="7" t="12" w="3554" /><ent r="7" t="12" w="3685" /><ent r="7" t="12" w="3685" /><ent r="7" t="12" w="6102" /><ent r="7" t="12" w="6102" /><ent r="8" t="12" w="7002" /><ent r="8" t="12" w="7002" /><ent r="7" t="12" w="7143" /><ent r="7" t="12" w="7143" /><ent r="8" t="12" w="9409" /><ent r="8" t="12" w="9409" /><ent r="8" t="12" w="9420" /><ent r="8" t="12" w="9420" /><ent r="8" t="12" w="9436" /><ent r="8" t="12" w="9436" /><ent r="8" t="12" w="10410" /><ent r="8" t="12" w="10410" /><ent r="8" t="12" w="10465" /><ent r="8" t="12" w="10465" /><ent r="8" t="12" w="10471" /><ent r="8" t="12" w="10471" /><ent r="7" t="12" w="11547" /><ent r="7" t="12" w="11547" /><ent r="7" t="12" w="11702" /><ent r="7" t="12" w="11702" /><ent r="7" t="13" w="1310" /><ent r="7" t="13" w="1310" /><ent r="8" t="13" w="3621" /><ent r="8" t="13" w="3621" /><ent r="7" t="13" w="5705" /><ent r="7" t="13" w="5705" /><ent r="8" t="13" w="8113" /><ent r="8" t="13" w="8169" /><ent r="8" t="13" w="8169" /><ent r="7" t="13" w="11725" /><ent r="7" t="13" w="11725" /><ent r="7" t="14" w="3096" /><ent r="7" t="14" w="3096" /><ent r="7" t="14" w="3186" /><ent r="7" t="14" w="3186" /><ent r="7" t="14" w="3349" /><ent r="7" t="14" w="3383" /><ent r="7" t="14" w="3383" /><ent r="7" t="14" w="3415" /><ent r="7" t="14" w="3415" /><ent r="7" t="14" w="3634" /><ent r="7" t="14" w="3634" /><ent r="7" t="14" w="3654" /><ent r="7" t="14" w="3654" /><ent r="7" t="14" w="4173" /><ent r="7" t="14" w="4173" /><ent r="7" t="14" w="4184" /><ent r="7" t="14" w="4184" /><ent r="8" t="14" w="5064" /><ent r="8" t="14" w="5064" /><ent r="8" t="14" w="5120" /><ent r="8" t="14" w="5120" /><ent r="8" t="14" w="5289" /><ent r="8" t="14" w="5289" /><ent r="7" t="14" w="5449" /><ent r="7" t="14" w="5449" /><ent r="7" t="14" w="5951" /><ent r="7" t="14" w="5951" /><ent r="7" t="14" w="5965" /><ent r="7" t="14" w="5965" /><ent r="8" t="14" w="6059" /><ent r="8" t="14" w="6059" /><ent r="8" t="14" w="6069" /><ent r="8" t="14" w="6069" /><ent r="7" t="14" w="6084" /><ent r="7" t="14" w="6084" /><ent r="7" t="14" w="6649" /><ent r="7" t="14" w="6649" /><ent r="7" t="14" w="7508" /><ent r="7" t="14" w="7508" /><ent r="7" t="14" w="7588" /><ent r="7" t="14" w="7588" /><ent r="7" t="14" w="7627" /><ent r="7" t="14" w="7627" /><ent r="7" t="14" w="7826" /><ent r="7" t="14" w="7826" /><ent r="7" t="14" w="7859" /><ent r="7" t="14" w="8315" /><ent r="7" t="14" w="8315" /><ent r="7" t="14" w="8354" /><ent r="7" t="14" w="8354" /><ent r="7" t="14" w="8715" /><ent r="7" t="14" w="9340" /><ent r="7" t="14" w="9340" /><ent r="7" t="14" w="9461" /><ent r="7" t="14" w="9461" /><ent r="7" t="14" w="9892" /><ent r="7" t="14" w="9892" /><ent r="7" t="14" w="9945" /><ent r="7" t="14" w="9945" /><ent r="7" t="14" w="10239" /><ent r="7" t="14" w="10239" /><ent r="7" t="16" w="193" /><ent r="7" t="16" w="193" /><ent r="8" t="16" w="1526" /><ent r="8" t="16" w="1526" /><ent r="7" t="16" w="4756" /><ent r="7" t="16" w="4756" /><ent r="8" t="16" w="5050" /><ent r="8" t="16" w="5050" /><ent r="7" t="16" w="6021" /><ent r="7" t="16" w="6021" /><ent r="7" t="16" w="6197" /><ent r="7" t="16" w="6197" /><ent r="7" t="16" w="8086" /><ent r="7" t="16" w="8086" /><ent r="8" t="16" w="9755" /><ent r="8" t="16" w="9755" /><ent r="8" t="16" w="9928" /><ent r="8" t="16" w="9928" /><ent r="8" t="16" w="10092" /><ent r="8" t="16" w="10092" /><ent r="8" t="16" w="10514" /><ent r="8" t="16" w="10514" /><ent r="8" t="16" w="10837" /><ent r="8" t="16" w="10837" /><ent r="8" t="16" w="10986" /><ent r="8" t="16" w="10986" /><ent r="8" t="16" w="11124" /><ent r="8" t="16" w="11124" /><ent r="7" t="16" w="11182" /><ent r="7" t="16" w="11182" /><ent r="7" t="16" w="11552" /><ent r="7" t="16" w="11552" /><ent r="7" t="16" w="11836" /><ent r="7" t="16" w="11836" /><ent r="7" t="17" w="2592" /><ent r="7" t="17" w="2592" /><ent r="7" t="17" w="3589" /><ent r="7" t="17" w="3589" /><ent r="7" t="17" w="7939" /><ent r="7" t="17" w="7939" /><ent r="7" t="17" w="9080" /><ent r="7" t="17" w="9080" /><ent r="7" t="17" w="9314" /><ent r="7" t="17" w="9314" /><ent r="7" t="18" w="4684" /><ent r="7" t="18" w="4684" /><ent r="7" t="18" w="5376" /><ent r="7" t="18" w="5376" /><ent r="7" t="18" w="7160" /><ent r="7" t="18" w="7160" /><ent r="7" t="18" w="8858" /><ent r="7" t="18" w="8858" /><ent r="7" t="18" w="9714" /><ent r="7" t="18" w="9714" /><ent r="7" t="18" w="10339" /><ent r="7" t="18" w="10339" /><ent r="7" t="18" w="10486" /><ent r="7" t="18" w="10486" /><ent r="8" t="18" w="10527" /><ent r="8" t="18" w="10527" /><ent r="7" t="18" w="10800" /><ent r="7" t="18" w="10800" /><ent r="7" t="20" w="535" /><ent r="7" t="20" w="535" /><ent r="7" t="20" w="745" /><ent r="7" t="20" w="745" /><ent r="8" t="20" w="2819" /><ent r="8" t="20" w="2819" /><ent r="7" t="20" w="4743" /><ent r="7" t="20" w="4743" /><ent r="7" t="21" w="787" /><ent r="7" t="21" w="787" /><ent r="7" t="21" w="1486" /><ent r="7" t="21" w="1486" /><ent r="7" t="21" w="1732" /><ent r="7" t="21" w="1732" /><ent r="8" t="21" w="4920" /><ent r="8" t="21" w="4920" /><ent r="7" t="21" w="6295" /><ent r="7" t="21" w="6295" /><ent r="7" t="25" w="1022" /><ent r="7" t="25" w="1022" /><ent r="7" t="25" w="1042" /><ent r="7" t="25" w="1042" /><ent r="7" t="25" w="3069" /><ent r="7" t="25" w="3069" /><ent r="7" t="25" w="3768" /><ent r="7" t="25" w="3768" /><ent r="7" t="25" w="4275" /><ent r="7" t="25" w="4275" /><ent r="7" t="25" w="4325" /><ent r="7" t="25" w="4325" /><ent r="7" t="25" w="4939" /></phr><phr n="Two"><ent r="7" t="12" w="10684" /><ent r="7" t="12" w="10684" /><ent r="8" t="17" w="6357" /><ent r="8" t="17" w="6357" /></phr></stem><stem n="vigor"><phr n="vigorous"><ent r="7" t="2" w="236" /><ent r="7" t="2" w="236" /></phr></stem><stem n="push"><phr n="pushing"><ent r="7" t="2" w="238" /><ent r="7" t="2" w="238" /></phr><phr n="push"><ent r="7" t="5" w="866" /><ent r="7" t="5" w="866" /><ent r="7" t="16" w="3762" /><ent r="7" t="16" w="3762" /></phr><phr n="pushes"><ent r="7" t="10" w="8443" /><ent r="7" t="10" w="8443" /></phr></stem><stem n="do"><phr n="do"><ent r="7" t="2" w="242" /><ent r="7" t="2" w="242" /><ent r="7" t="2" w="540" /><ent r="7" t="2" w="540" /><ent r="8" t="5" w="286" /><ent r="8" t="5" w="286" /><ent r="7" t="5" w="299" /><ent r="7" t="5" w="299" /><ent r="7" t="5" w="604" /><ent r="7" t="5" w="604" /><ent r="7" t="5" w="922" /><ent r="7" t="5" w="922" /><ent r="7" t="5" w="1128" /><ent r="7" t="5" w="1128" /><ent r="7" t="5" w="1193" /><ent r="7" t="5" w="1193" /><ent r="7" t="6" w="208" /><ent r="7" t="6" w="208" /><ent r="7" t="6" w="254" /><ent r="7" t="6" w="254" /><ent r="7" t="6" w="510" /><ent r="7" t="6" w="510" /><ent r="7" t="6" w="638" /><ent r="7" t="6" w="751" /><ent r="7" t="6" w="751" /><ent r="7" t="6" w="833" /><ent r="7" t="6" w="833" /><ent r="8" t="6" w="1242" /><ent r="7" t="8" w="212" /><ent r="8" t="8" w="454" /><ent r="7" t="8" w="534" /><ent r="7" t="8" w="534" /><ent r="8" t="8" w="878" /><ent r="8" t="8" w="878" /><ent r="7" t="8" w="979" /><ent r="7" t="8" w="979" /><ent r="7" t="8" w="1067" /><ent r="7" t="8" w="1311" /><ent r="7" t="8" w="1311" /><ent r="7" t="8" w="1388" /><ent r="7" t="8" w="1388" /><ent r="7" t="8" w="1432" /><ent r="7" t="8" w="1654" /><ent r="7" t="8" w="1688" /><ent r="7" t="8" w="1688" /><ent r="7" t="8" w="1719" /><ent r="7" t="8" w="1719" /><ent r="7" t="8" w="1962" /><ent r="7" t="8" w="1962" /><ent r="7" t="8" w="2146" /><ent r="8" t="8" w="2220" /><ent r="8" t="8" w="2220" /><ent r="7" t="8" w="2372" /><ent r="7" t="8" w="2414" /><ent r="7" t="8" w="2414" /><ent r="7" t="8" w="2461" /><ent r="7" t="8" w="2461" /><ent r="7" t="8" w="2569" /><ent r="7" t="8" w="2569" /><ent r="8" t="8" w="2715" /><ent r="8" t="8" w="2715" /><ent r="8" t="8" w="2751" /><ent r="8" t="8" w="2751" /><ent r="7" t="8" w="3329" /><ent r="7" t="8" w="3329" /><ent r="7" t="8" w="3491" /><ent r="7" t="8" w="3491" /><ent r="7" t="8" w="3634" /><ent r="7" t="8" w="3634" /><ent r="7" t="8" w="3688" /><ent r="7" t="8" w="3688" /><ent r="8" t="8" w="3822" /><ent r="8" t="8" w="3822" /><ent r="8" t="8" w="4004" /><ent r="8" t="8" w="4018" /><ent r="7" t="8" w="4073" /><ent r="7" t="8" w="4073" /><ent r="7" t="8" w="4117" /><ent r="7" t="8" w="4334" /><ent r="7" t="8" w="4334" /><ent r="7" t="8" w="4551" /><ent r="7" t="8" w="4551" /><ent r="8" t="8" w="4857" /><ent r="8" t="8" w="5177" /><ent r="7" t="8" w="5308" /><ent r="7" t="8" w="5308" /><ent r="7" t="8" w="5504" /><ent r="7" t="8" w="5504" /><ent r="7" t="8" w="5747" /><ent r="7" t="8" w="5850" /><ent r="7" t="8" w="5850" /><ent r="7" t="8" w="5927" /><ent r="7" t="8" w="5927" /><ent r="8" t="8" w="6547" /><ent r="8" t="8" w="6547" /><ent r="8" t="8" w="6563" /><ent r="8" t="8" w="6563" /><ent r="7" t="8" w="6584" /><ent r="8" t="8" w="7318" /><ent r="8" t="8" w="7318" /><ent r="8" t="8" w="7960" /><ent r="8" t="8" w="7960" /><ent r="8" t="8" w="7987" /><ent r="8" t="8" w="7987" /><ent r="8" t="8" w="8125" /><ent r="8" t="8" w="8125" /><ent r="7" t="8" w="8924" /><ent r="7" t="8" w="8924" /><ent r="7" t="8" w="8933" /><ent r="7" t="8" w="8933" /><ent r="7" t="8" w="9156" /><ent r="7" t="8" w="9156" /><ent r="8" t="8" w="9250" /><ent r="8" t="8" w="9250" /><ent r="7" t="8" w="9290" /><ent r="7" t="8" w="9290" /><ent r="7" t="8" w="9369" /><ent r="7" t="8" w="9369" /><ent r="7" t="8" w="9634" /><ent r="7" t="8" w="9634" /><ent r="7" t="8" w="9659" /><ent r="7" t="8" w="9659" /><ent r="7" t="8" w="9951" /><ent r="7" t="8" w="9958" /><ent r="7" t="9" w="1262" /><ent r="7" t="9" w="1262" /><ent r="7" t="9" w="1329" /><ent r="7" t="9" w="1329" /><ent r="7" t="9" w="1347" /><ent r="7" t="9" w="1347" /><ent r="8" t="9" w="1420" /><ent r="8" t="9" w="1420" /><ent r="7" t="9" w="1906" /><ent r="7" t="9" w="1906" /><ent r="7" t="9" w="1920" /><ent r="7" t="9" w="1920" /><ent r="8" t="9" w="2088" /><ent r="8" t="9" w="2088" /><ent r="8" t="9" w="2095" /><ent r="8" t="9" w="2095" /><ent r="8" t="9" w="2907" /><ent r="8" t="9" w="2907" /><ent r="7" t="9" w="5503" /><ent r="7" t="9" w="5503" /><ent r="7" t="9" w="6109" /><ent r="7" t="9" w="6109" /><ent r="7" t="9" w="7624" /><ent r="7" t="10" w="278" /><ent r="7" t="10" w="278" /><ent r="7" t="10" w="294" /><ent r="7" t="10" w="294" /><ent r="7" t="10" w="970" /><ent r="7" t="10" w="970" /><ent r="7" t="10" w="1717" /><ent r="7" t="10" w="1717" /><ent r="8" t="10" w="2691" /><ent r="8" t="10" w="2691" /><ent r="7" t="10" w="2933" /><ent r="7" t="10" w="2933" /><ent r="7" t="10" w="3085" /><ent r="7" t="10" w="3289" /><ent r="7" t="10" w="3289" /><ent r="7" t="10" w="3572" /><ent r="7" t="10" w="3572" /><ent r="7" t="10" w="3933" /><ent r="7" t="10" w="3933" /><ent r="7" t="10" w="3948" /><ent r="7" t="10" w="3948" /><ent r="8" t="10" w="4061" /><ent r="8" t="10" w="4061" /><ent r="7" t="10" w="4885" /><ent r="7" t="10" w="4885" /><ent r="7" t="10" w="4899" /><ent r="7" t="10" w="4899" /><ent r="7" t="10" w="4938" /><ent r="7" t="10" w="4938" /><ent r="7" t="10" w="4953" /><ent r="7" t="10" w="4953" /><ent r="7" t="10" w="5670" /><ent r="7" t="10" w="5670" /><ent r="7" t="10" w="5672" /><ent r="7" t="10" w="5672" /><ent r="7" t="10" w="6008" /><ent r="7" t="10" w="6008" /><ent r="69" t="10" w="6138" /><ent r="69" t="10" w="6138" /><ent r="67" t="10" w="6152" /><ent r="67" t="10" w="6152" /><ent r="7" t="10" w="6190" /><ent r="7" t="10" w="6190" /><ent r="7" t="10" w="6202" /><ent r="7" t="10" w="6498" /><ent r="7" t="10" w="6498" /><ent r="7" t="10" w="6985" /><ent r="7" t="10" w="6985" /><ent r="7" t="10" w="7141" /><ent r="7" t="10" w="7141" /><ent r="7" t="10" w="7233" /><ent r="7" t="10" w="7233" /><ent r="7" t="10" w="7378" /><ent r="7" t="10" w="7378" /><ent r="7" t="10" w="7689" /><ent r="7" t="10" w="7689" /><ent r="7" t="10" w="8457" /><ent r="7" t="10" w="8457" /><ent r="8" t="12" w="1087" /><ent r="8" t="12" w="1087" /><ent r="8" t="12" w="1147" /><ent r="8" t="12" w="1147" /><ent r="8" t="12" w="1358" /><ent r="8" t="12" w="1358" /><ent r="8" t="12" w="2106" /><ent r="8" t="12" w="2106" /><ent r="8" t="12" w="2137" /><ent r="7" t="12" w="2692" /><ent r="7" t="12" w="2692" /><ent r="8" t="12" w="3244" /><ent r="8" t="12" w="3244" /><ent r="8" t="12" w="3321" /><ent r="8" t="12" w="3321" /><ent r="8" t="12" w="3414" /><ent r="8" t="12" w="3414" /><ent r="8" t="12" w="3435" /><ent r="8" t="12" w="3435" /><ent r="7" t="12" w="4604" /><ent r="7" t="12" w="4604" /><ent r="7" t="12" w="6302" /><ent r="7" t="12" w="6302" /><ent r="7" t="12" w="6881" /><ent r="7" t="12" w="6881" /><ent r="7" t="12" w="6910" /><ent r="7" t="12" w="6910" /><ent r="7" t="12" w="6919" /><ent r="7" t="12" w="6919" /><ent r="7" t="12" w="7078" /><ent r="7" t="12" w="7078" /><ent r="7" t="12" w="7203" /><ent r="7" t="12" w="7203" /><ent r="7" t="12" w="7218" /><ent r="7" t="12" w="7249" /><ent r="7" t="12" w="7286" /><ent r="7" t="12" w="7286" /><ent r="8" t="12" w="7506" /><ent r="8" t="12" w="9911" /><ent r="8" t="12" w="9911" /><ent r="7" t="12" w="10317" /><ent r="7" t="12" w="10317" /><ent r="7" t="12" w="11079" /><ent r="7" t="12" w="11079" /><ent r="7" t="13" w="380" /><ent r="7" t="13" w="380" /><ent r="7" t="13" w="473" /><ent r="7" t="13" w="473" /><ent r="7" t="13" w="1088" /><ent r="7" t="13" w="1088" /><ent r="7" t="13" w="1448" /><ent r="7" t="13" w="1448" /><ent r="7" t="13" w="2119" /><ent r="7" t="13" w="2119" /><ent r="7" t="13" w="2129" /><ent r="7" t="13" w="2129" /><ent r="8" t="13" w="2433" /><ent r="8" t="13" w="2433" /><ent r="7" t="13" w="2624" /><ent r="7" t="13" w="2624" /><ent r="8" t="13" w="3040" /><ent r="8" t="13" w="3040" /><ent r="7" t="13" w="3329" /><ent r="7" t="13" w="3329" /><ent r="8" t="13" w="3715" /><ent r="8" t="13" w="3715" /><ent r="7" t="13" w="3995" /><ent r="7" t="13" w="3995" /><ent r="7" t="13" w="4084" /><ent r="7" t="13" w="4084" /><ent r="7" t="13" w="4344" /><ent r="7" t="13" w="4344" /><ent r="7" t="13" w="5441" /><ent r="7" t="13" w="5441" /><ent r="7" t="13" w="5453" /><ent r="7" t="13" w="5453" /><ent r="7" t="13" w="5838" /><ent r="7" t="13" w="5838" /><ent r="7" t="13" w="8385" /><ent r="7" t="13" w="8385" /><ent r="8" t="13" w="8441" /><ent r="8" t="13" w="8441" /><ent r="8" t="13" w="8831" /><ent r="8" t="13" w="8831" /><ent r="8" t="13" w="9344" /><ent r="8" t="13" w="9344" /><ent r="8" t="14" w="1418" /><ent r="8" t="14" w="1418" /><ent r="7" t="14" w="4214" /><ent r="7" t="14" w="4214" /><ent r="7" t="14" w="6449" /><ent r="7" t="14" w="6449" /><ent r="7" t="14" w="6523" /><ent r="7" t="14" w="6523" /><ent r="8" t="14" w="9636" /><ent r="8" t="14" w="9636" /><ent r="8" t="16" w="1386" /><ent r="8" t="16" w="1386" /><ent r="7" t="16" w="3317" /><ent r="7" t="16" w="3437" /><ent r="7" t="16" w="3437" /><ent r="7" t="16" w="3504" /><ent r="7" t="16" w="3504" /><ent r="7" t="16" w="4030" /><ent r="7" t="16" w="4044" /><ent r="7" t="16" w="4044" /><ent r="7" t="16" w="4103" /><ent r="7" t="16" w="4132" /><ent r="7" t="16" w="4132" /><ent r="7" t="16" w="4518" /><ent r="7" t="16" w="4518" /><ent r="7" t="16" w="4737" /><ent r="7" t="16" w="4737" /><ent r="7" t="16" w="4926" /><ent r="7" t="16" w="4926" /><ent r="7" t="16" w="5273" /><ent r="7" t="16" w="5273" /><ent r="8" t="16" w="5684" /><ent r="8" t="16" w="5684" /><ent r="7" t="16" w="5843" /><ent r="7" t="16" w="5843" /><ent r="7" t="16" w="6499" /><ent r="7" t="16" w="6499" /><ent r="7" t="16" w="7266" /><ent r="7" t="16" w="7266" /><ent r="7" t="16" w="7993" /><ent r="7" t="16" w="7993" /><ent r="8" t="16" w="8307" /><ent r="8" t="16" w="8307" /><ent r="7" t="16" w="8536" /><ent r="7" t="16" w="8536" /><ent r="7" t="16" w="8658" /><ent r="7" t="16" w="8658" /><ent r="7" t="16" w="8779" /><ent r="7" t="16" w="8779" /><ent r="7" t="16" w="8932" /><ent r="7" t="16" w="8932" /><ent r="7" t="16" w="9238" /><ent r="7" t="16" w="9238" /><ent r="9" t="16" w="9257" /><ent r="9" t="16" w="9257" /><ent r="8" t="16" w="10006" /><ent r="8" t="16" w="10006" /><ent r="8" t="16" w="10173" /><ent r="8" t="16" w="10173" /><ent r="8" t="16" w="10586" /><ent r="8" t="16" w="10586" /><ent r="7" t="16" w="11224" /><ent r="7" t="16" w="11224" /><ent r="7" t="16" w="11388" /><ent r="7" t="16" w="11388" /><ent r="10" t="17" w="1368" /><ent r="10" t="17" w="1368" /><ent r="8" t="17" w="1972" /><ent r="8" t="17" w="1972" /><ent r="7" t="17" w="2141" /><ent r="7" t="17" w="2141" /><ent r="7" t="17" w="2430" /><ent r="7" t="17" w="2430" /><ent r="7" t="17" w="3310" /><ent r="7" t="17" w="3384" /><ent r="7" t="17" w="3384" /><ent r="7" t="17" w="3689" /><ent r="7" t="17" w="3689" /><ent r="9" t="17" w="8078" /><ent r="9" t="17" w="8078" /><ent r="9" t="17" w="8253" /><ent r="9" t="17" w="8253" /><ent r="7" t="18" w="213" /><ent r="7" t="18" w="213" /><ent r="7" t="18" w="305" /><ent r="7" t="18" w="305" /><ent r="7" t="18" w="3118" /><ent r="7" t="18" w="3118" /><ent r="7" t="18" w="4061" /><ent r="7" t="18" w="4061" /><ent r="7" t="18" w="4285" /><ent r="7" t="18" w="4285" /><ent r="7" t="18" w="5352" /><ent r="7" t="18" w="5352" /><ent r="7" t="18" w="6465" /><ent r="7" t="18" w="6898" /><ent r="7" t="18" w="6898" /><ent r="7" t="18" w="9165" /><ent r="7" t="18" w="9165" /><ent r="7" t="18" w="10718" /><ent r="7" t="18" w="10718" /><ent r="7" t="20" w="1206" /><ent r="7" t="20" w="1206" /><ent r="7" t="20" w="2053" /><ent r="7" t="20" w="2053" /><ent r="7" t="20" w="2419" /><ent r="7" t="20" w="2419" /><ent r="7" t="20" w="2446" /><ent r="7" t="20" w="2446" /><ent r="7" t="20" w="2460" /><ent r="7" t="20" w="2460" /><ent r="7" t="20" w="2587" /><ent r="7" t="20" w="2587" /><ent r="9" t="20" w="4082" /><ent r="9" t="20" w="4082" /><ent r="7" t="20" w="4580" /><ent r="7" t="20" w="4580" /><ent r="7" t="20" w="4582" /><ent r="7" t="20" w="4582" /><ent r="7" t="20" w="5208" /><ent r="7" t="20" w="5208" /><ent r="7" t="21" w="355" /><ent r="7" t="21" w="355" /><ent r="7" t="21" w="1707" /><ent r="7" t="21" w="1707" /><ent r="7" t="21" w="2477" /><ent r="7" t="21" w="2477" /><ent r="7" t="21" w="3626" /><ent r="7" t="21" w="3626" /><ent r="7" t="21" w="3894" /><ent r="7" t="21" w="3894" /><ent r="7" t="25" w="1564" /><ent r="7" t="25" w="1564" /><ent r="7" t="25" w="2334" /><ent r="7" t="25" w="2334" /><ent r="7" t="25" w="2488" /><ent r="7" t="25" w="2488" /><ent r="7" t="25" w="3427" /><ent r="7" t="25" w="3427" /><ent r="7" t="25" w="3430" /><ent r="7" t="25" w="3430" /><ent r="7" t="25" w="3458" /><ent r="7" t="25" w="3458" /><ent r="7" t="25" w="3532" /><ent r="7" t="25" w="3532" /><ent r="7" t="25" w="4447" /><ent r="7" t="25" w="4447" /><ent r="7" t="25" w="4576" /><ent r="7" t="25" w="4576" /><ent r="7" t="25" w="4868" /><ent r="7" t="25" w="4868" /><ent r="7" t="25" w="4903" /><ent r="7" t="25" w="4903" /><ent r="7" t="25" w="4945" /><ent r="7" t="25" w="4945" /><ent r="7" t="25" w="5529" /><ent r="7" t="25" w="5529" /><ent r="7" t="25" w="5549" /><ent r="7" t="25" w="5549" /><ent r="7" t="25" w="5761" /><ent r="7" t="25" w="5761" /></phr><phr n="doing"><ent r="7" t="6" w="672" /><ent r="7" t="6" w="672" /><ent r="7" t="6" w="743" /><ent r="7" t="6" w="743" /><ent r="200" t="7" w="35" /><ent r="200" t="7" w="35" /><ent r="7" t="7" w="169" /><ent r="7" t="7" w="169" /><ent r="7" t="8" w="1422" /><ent r="7" t="8" w="1422" /><ent r="7" t="8" w="1660" /><ent r="7" t="8" w="1660" /><ent r="7" t="8" w="4453" /><ent r="7" t="8" w="4509" /><ent r="7" t="8" w="4509" /><ent r="7" t="8" w="6398" /><ent r="7" t="8" w="6398" /><ent r="7" t="8" w="7432" /><ent r="7" t="9" w="1065" /><ent r="7" t="9" w="1065" /><ent r="7" t="10" w="562" /><ent r="7" t="10" w="562" /><ent r="7" t="10" w="2153" /><ent r="7" t="10" w="2153" /><ent r="8" t="10" w="2883" /><ent r="8" t="10" w="2883" /><ent r="8" t="10" w="3820" /><ent r="8" t="12" w="6137" /><ent r="8" t="12" w="6137" /><ent r="7" t="12" w="6929" /><ent r="7" t="12" w="6929" /><ent r="7" t="13" w="3957" /><ent r="7" t="13" w="3957" /><ent r="7" t="13" w="5357" /><ent r="7" t="13" w="5627" /><ent r="7" t="13" w="5627" /><ent r="8" t="13" w="6496" /><ent r="8" t="13" w="6496" /><ent r="7" t="13" w="8272" /><ent r="7" t="14" w="1256" /><ent r="7" t="14" w="1256" /><ent r="7" t="16" w="1671" /><ent r="7" t="16" w="1671" /><ent r="7" t="17" w="2251" /><ent r="7" t="17" w="2251" /><ent r="7" t="17" w="5669" /><ent r="8" t="18" w="2855" /><ent r="8" t="18" w="2855" /><ent r="7" t="20" w="748" /><ent r="7" t="20" w="748" /><ent r="7" t="20" w="4114" /><ent r="7" t="20" w="4114" /><ent r="7" t="21" w="3382" /><ent r="7" t="21" w="3382" /><ent r="7" t="25" w="420" /><ent r="7" t="25" w="420" /><ent r="7" t="25" w="5432" /><ent r="7" t="25" w="5432" /></phr><phr n="Do"><ent r="8" t="8" w="4736" /><ent r="8" t="8" w="4736" /><ent r="8" t="8" w="5108" /><ent r="8" t="8" w="5108" /><ent r="7" t="9" w="1289" /><ent r="7" t="9" w="1289" /><ent r="8" t="10" w="3792" /><ent r="8" t="10" w="3792" /><ent r="7" t="10" w="4857" /><ent r="7" t="10" w="4857" /><ent r="7" t="10" w="7667" /><ent r="7" t="10" w="7667" /><ent r="8" t="12" w="7113" /><ent r="8" t="12" w="7113" /><ent r="8" t="12" w="7504" /><ent r="8" t="12" w="7504" /><ent r="7" t="12" w="9995" /><ent r="7" t="12" w="9995" /><ent r="8" t="13" w="5383" /><ent r="8" t="13" w="5383" /><ent r="8" t="13" w="5476" /><ent r="8" t="13" w="5476" /><ent r="7" t="14" w="9179" /><ent r="7" t="14" w="9179" /><ent r="8" t="16" w="2737" /><ent r="8" t="16" w="2737" /><ent r="7" t="17" w="4237" /><ent r="7" t="17" w="4237" /><ent r="7" t="21" w="2160" /><ent r="7" t="21" w="2160" /><ent r="7" t="21" w="3357" /><ent r="7" t="21" w="3357" /><ent r="7" t="21" w="3386" /><ent r="7" t="21" w="3386" /><ent r="7" t="21" w="3616" /><ent r="7" t="21" w="3616" /><ent r="7" t="21" w="3885" /><ent r="7" t="21" w="3885" /><ent r="7" t="21" w="3933" /><ent r="7" t="21" w="3933" /><ent r="7" t="21" w="4725" /><ent r="7" t="21" w="4725" /><ent r="7" t="21" w="6033" /><ent r="7" t="21" w="6033" /><ent r="7" t="21" w="6286" /><ent r="7" t="21" w="6286" /></phr></stem><stem n="necessari"><phr n="necessary"><ent r="7" t="2" w="245" /><ent r="7" t="2" w="245" /><ent r="7" t="5" w="1461" /><ent r="7" t="5" w="2095" /><ent r="7" t="5" w="2309" /><ent r="7" t="5" w="2309" /><ent r="68" t="7" w="447" /><ent r="68" t="7" w="447" /><ent r="7" t="8" w="1991" /><ent r="7" t="8" w="1991" /><ent r="7" t="8" w="4244" /><ent r="7" t="8" w="4244" /><ent r="7" t="8" w="4377" /><ent r="7" t="9" w="1248" /><ent r="7" t="9" w="3541" /><ent r="7" t="9" w="4875" /><ent r="7" t="10" w="1445" /><ent r="7" t="10" w="1445" /><ent r="7" t="10" w="1479" /><ent r="7" t="10" w="1552" /><ent r="7" t="10" w="1776" /><ent r="7" t="10" w="2098" /><ent r="8" t="10" w="2102" /><ent r="8" t="10" w="2102" /><ent r="7" t="10" w="3056" /><ent r="7" t="10" w="3056" /><ent r="7" t="10" w="3536" /><ent r="7" t="10" w="3536" /><ent r="7" t="10" w="3580" /><ent r="7" t="10" w="3580" /><ent r="8" t="10" w="3812" /><ent r="8" t="10" w="3812" /><ent r="69" t="10" w="4180" /><ent r="69" t="10" w="4180" /><ent r="8" t="10" w="5329" /><ent r="8" t="10" w="5329" /><ent r="8" t="10" w="6171" /><ent r="8" t="10" w="6171" /><ent r="77" t="10" w="7600" /><ent r="77" t="10" w="7600" /><ent r="7" t="10" w="8738" /><ent r="7" t="10" w="8738" /><ent r="8" t="10" w="9411" /><ent r="8" t="10" w="9411" /><ent r="7" t="12" w="1877" /><ent r="7" t="12" w="1877" /><ent r="7" t="12" w="4978" /><ent r="7" t="12" w="4978" /><ent r="7" t="12" w="7485" /><ent r="7" t="12" w="7485" /><ent r="8" t="12" w="8978" /><ent r="8" t="12" w="8978" /><ent r="7" t="12" w="9939" /><ent r="7" t="12" w="9939" /><ent r="7" t="12" w="10059" /><ent r="7" t="12" w="10059" /><ent r="7" t="13" w="5886" /><ent r="7" t="13" w="5886" /><ent r="7" t="14" w="1836" /><ent r="7" t="14" w="1836" /><ent r="7" t="14" w="5243" /><ent r="7" t="14" w="5243" /><ent r="7" t="16" w="984" /><ent r="7" t="16" w="984" /><ent r="7" t="16" w="2528" /><ent r="7" t="16" w="2528" /><ent r="7" t="16" w="8430" /><ent r="7" t="16" w="8430" /><ent r="7" t="17" w="3663" /><ent r="7" t="17" w="3663" /><ent r="7" t="17" w="4532" /><ent r="7" t="17" w="4532" /><ent r="7" t="17" w="6050" /><ent r="7" t="17" w="6050" /><ent r="7" t="18" w="2781" /><ent r="7" t="18" w="2781" /><ent r="7" t="18" w="6803" /><ent r="7" t="20" w="262" /><ent r="7" t="20" w="730" /><ent r="7" t="20" w="933" /><ent r="7" t="21" w="3359" /><ent r="7" t="21" w="3359" /><ent r="7" t="21" w="3395" /><ent r="7" t="21" w="3395" /><ent r="7" t="21" w="4377" /><ent r="7" t="21" w="4377" /><ent r="7" t="25" w="748" /><ent r="7" t="25" w="748" /><ent r="7" t="25" w="3977" /><ent r="68" t="27" w="464" /><ent r="68" t="27" w="464" /></phr><phr n="Necessary"><ent r="8" t="17" w="5063" /><ent r="8" t="17" w="5063" /></phr></stem></index>