<?xml version="1.0" encoding="utf-8"?><index><!-- saved from url=(0016)http://localhost -->
<stem n="higher"><phr n="higher"><ent r="7" t="8" w="6383" /><ent r="7" t="8" w="7763" /><ent r="7" t="8" w="7832" /><ent r="7" t="16" w="1791" /><ent r="7" t="16" w="1791" /><ent r="7" t="16" w="3482" /><ent r="7" t="16" w="3482" /><ent r="7" t="16" w="8769" /><ent r="7" t="17" w="3425" /><ent r="7" t="17" w="3425" /><ent r="7" t="18" w="6792" /><ent r="7" t="18" w="6792" /></phr><phr n="Higher"><ent r="7" t="8" w="6386" /></phr></stem><stem n="flow"><phr n="flow"><ent r="7" t="8" w="6411" /><ent r="7" t="8" w="6411" /><ent r="7" t="8" w="7875" /><ent r="7" t="8" w="7875" /><ent r="7" t="8" w="8088" /><ent r="7" t="8" w="8088" /><ent r="7" t="9" w="1993" /><ent r="7" t="9" w="1993" /><ent r="7" t="9" w="4348" /><ent r="7" t="10" w="2221" /><ent r="7" t="10" w="2221" /><ent r="7" t="10" w="5621" /><ent r="7" t="10" w="5621" /><ent r="7" t="10" w="7523" /><ent r="7" t="10" w="7523" /><ent r="7" t="10" w="7596" /><ent r="7" t="12" w="279" /><ent r="7" t="12" w="279" /><ent r="7" t="12" w="4026" /><ent r="7" t="12" w="4026" /><ent r="7" t="12" w="4625" /><ent r="7" t="12" w="4625" /><ent r="7" t="12" w="4890" /><ent r="7" t="12" w="4890" /><ent r="7" t="16" w="1249" /><ent r="7" t="16" w="1249" /><ent r="7" t="16" w="11448" /><ent r="7" t="16" w="11448" /><ent r="7" t="16" w="11651" /><ent r="7" t="16" w="11651" /><ent r="8" t="18" w="2019" /><ent r="8" t="18" w="2024" /><ent r="8" t="18" w="2024" /><ent r="8" t="18" w="2055" /><ent r="8" t="18" w="2055" /><ent r="7" t="18" w="2093" /><ent r="7" t="18" w="2093" /><ent r="7" t="18" w="2149" /><ent r="7" t="18" w="2149" /><ent r="7" t="18" w="2819" /><ent r="7" t="18" w="2819" /><ent r="8" t="18" w="5392" /><ent r="8" t="18" w="5397" /><ent r="8" t="18" w="5397" /><ent r="10" t="18" w="5417" /><ent r="10" t="18" w="5417" /><ent r="7" t="18" w="7344" /><ent r="7" t="18" w="7344" /><ent r="7" t="18" w="7348" /><ent r="7" t="18" w="7348" /><ent r="7" t="21" w="1651" /><ent r="7" t="21" w="1651" /><ent r="7" t="21" w="6178" /><ent r="7" t="21" w="6178" /><ent r="7" t="25" w="656" /><ent r="7" t="25" w="656" /></phr><phr n="flows"><ent r="8" t="18" w="1914" /><ent r="67" t="18" w="2006" /><ent r="67" t="18" w="2006" /><ent r="7" t="18" w="3442" /></phr></stem><stem n="subordin"><phr n="subordinate"><ent r="7" t="8" w="6461" /><ent r="7" t="8" w="6461" /><ent r="7" t="8" w="7851" /><ent r="7" t="8" w="7851" /><ent r="7" t="12" w="4170" /><ent r="7" t="12" w="4170" /><ent r="7" t="12" w="4281" /><ent r="7" t="12" w="4281" /><ent r="7" t="12" w="4745" /><ent r="7" t="12" w="4745" /><ent r="7" t="14" w="4835" /><ent r="7" t="14" w="4835" /><ent r="7" t="14" w="4872" /><ent r="7" t="14" w="4872" /><ent r="57" t="14" w="5161" /><ent r="57" t="14" w="5161" /><ent r="8" t="14" w="5171" /><ent r="8" t="14" w="5171" /><ent r="8" t="14" w="5188" /><ent r="8" t="14" w="5188" /><ent r="7" t="14" w="5202" /><ent r="7" t="14" w="5202" /><ent r="7" t="14" w="5220" /><ent r="7" t="14" w="5360" /><ent r="7" t="14" w="5360" /><ent r="68" t="15" w="278" /><ent r="68" t="15" w="278" /><ent r="69" t="16" w="612" /><ent r="69" t="16" w="612" /><ent r="7" t="16" w="6192" /><ent r="7" t="16" w="6192" /><ent r="87" t="16" w="9434" /><ent r="87" t="16" w="9434" /><ent r="7" t="20" w="4181" /><ent r="7" t="20" w="4181" /><ent r="68" t="27" w="785" /><ent r="68" t="27" w="785" /></phr><phr n="Subordinating"><ent r="7" t="12" w="4007" /><ent r="7" t="12" w="4007" /></phr><phr n="Subordinate"><ent r="7" t="12" w="4269" /><ent r="7" t="12" w="4269" /><ent r="7" t="14" w="5021" /><ent r="7" t="14" w="5021" /></phr><phr n="subordination"><ent r="8" t="16" w="9443" /><ent r="8" t="16" w="9443" /></phr></stem><stem n="substep"><phr n="substeps"><ent r="7" t="8" w="6467" /><ent r="7" t="8" w="6467" /><ent r="7" t="8" w="8307" /><ent r="7" t="8" w="8419" /><ent r="7" t="8" w="8419" /><ent r="7" t="8" w="8442" /><ent r="7" t="8" w="8442" /><ent r="7" t="8" w="8551" /><ent r="7" t="8" w="8551" /><ent r="7" t="8" w="9114" /></phr></stem><stem n="subtask"><phr n="subtasks"><ent r="7" t="8" w="6470" /><ent r="8" t="10" w="2877" /><ent r="7" t="10" w="3079" /><ent r="7" t="10" w="3079" /><ent r="7" t="10" w="3566" /><ent r="7" t="10" w="3566" /><ent r="7" t="16" w="4785" /><ent r="7" t="16" w="4785" /><ent r="7" t="16" w="6178" /><ent r="7" t="16" w="8538" /><ent r="7" t="16" w="8538" /><ent r="7" t="16" w="8762" /><ent r="7" t="16" w="8762" /><ent r="7" t="16" w="8920" /><ent r="7" t="16" w="8920" /><ent r="7" t="18" w="2080" /></phr><phr n="subtask"><ent r="8" t="25" w="4673" /><ent r="7" t="25" w="4689" /><ent r="7" t="25" w="4689" /><ent r="69" t="25" w="4833" /><ent r="69" t="25" w="4833" /></phr></stem><stem n="item"><phr n="item"><ent r="7" t="8" w="6592" /><ent r="7" t="8" w="6592" /><ent r="7" t="8" w="7390" /><ent r="7" t="8" w="7390" /><ent r="7" t="8" w="8565" /><ent r="7" t="8" w="8565" /><ent r="7" t="9" w="3598" /><ent r="7" t="9" w="3610" /><ent r="7" t="9" w="3619" /><ent r="7" t="9" w="3628" /><ent r="7" t="9" w="3628" /><ent r="8" t="13" w="3764" /><ent r="8" t="13" w="3764" /><ent r="8" t="13" w="3851" /><ent r="8" t="13" w="3851" /><ent r="7" t="13" w="7231" /><ent r="7" t="13" w="7231" /><ent r="8" t="14" w="4451" /><ent r="8" t="14" w="4451" /><ent r="8" t="14" w="5440" /><ent r="8" t="14" w="5440" /><ent r="7" t="14" w="7523" /><ent r="7" t="14" w="7523" /><ent r="7" t="14" w="7539" /><ent r="7" t="14" w="7539" /><ent r="7" t="14" w="7621" /><ent r="7" t="14" w="7621" /><ent r="7" t="14" w="7736" /><ent r="7" t="14" w="7736" /><ent r="7" t="17" w="1098" /><ent r="7" t="17" w="1098" /><ent r="7" t="18" w="8587" /><ent r="7" t="18" w="8587" /><ent r="7" t="21" w="2187" /><ent r="7" t="21" w="2187" /></phr><phr n="items"><ent r="7" t="9" w="3588" /><ent r="7" t="10" w="222" /><ent r="7" t="10" w="222" /><ent r="7" t="10" w="7674" /><ent r="7" t="12" w="1328" /><ent r="7" t="12" w="1328" /><ent r="7" t="12" w="2615" /><ent r="8" t="12" w="8267" /><ent r="8" t="12" w="8267" /><ent r="8" t="12" w="9421" /><ent r="8" t="12" w="9421" /><ent r="8" t="12" w="9439" /><ent r="8" t="12" w="9439" /><ent r="8" t="12" w="9457" /><ent r="8" t="12" w="9457" /><ent r="8" t="13" w="7167" /><ent r="8" t="13" w="7167" /><ent r="7" t="13" w="7220" /><ent r="7" t="13" w="7220" /><ent r="7" t="13" w="11108" /><ent r="7" t="13" w="11108" /><ent r="8" t="14" w="2331" /><ent r="7" t="14" w="4239" /><ent r="7" t="14" w="4239" /><ent r="67" t="14" w="5397" /><ent r="67" t="14" w="5397" /><ent r="7" t="14" w="5876" /><ent r="7" t="14" w="7509" /><ent r="7" t="14" w="7509" /><ent r="7" t="14" w="7516" /><ent r="7" t="14" w="7516" /><ent r="7" t="14" w="7553" /><ent r="7" t="14" w="7559" /><ent r="7" t="14" w="7559" /><ent r="7" t="14" w="7593" /><ent r="7" t="14" w="7609" /><ent r="7" t="14" w="7609" /><ent r="7" t="14" w="7745" /><ent r="7" t="14" w="7745" /><ent r="7" t="14" w="7916" /><ent r="7" t="14" w="7916" /><ent r="7" t="14" w="7928" /><ent r="7" t="14" w="7928" /><ent r="8" t="14" w="8556" /><ent r="8" t="14" w="8556" /><ent r="7" t="16" w="5859" /><ent r="7" t="16" w="5859" /><ent r="7" t="16" w="10209" /><ent r="7" t="16" w="10209" /><ent r="7" t="17" w="8604" /><ent r="7" t="17" w="8604" /><ent r="7" t="17" w="9023" /><ent r="7" t="17" w="9023" /><ent r="7" t="18" w="6222" /><ent r="7" t="18" w="6222" /><ent r="8" t="20" w="3433" /><ent r="8" t="20" w="3433" /><ent r="8" t="20" w="3562" /><ent r="8" t="20" w="3562" /><ent r="8" t="20" w="3581" /><ent r="8" t="20" w="3581" /><ent r="7" t="20" w="5487" /><ent r="7" t="21" w="280" /><ent r="7" t="21" w="2154" /><ent r="7" t="21" w="2154" /><ent r="7" t="21" w="2426" /><ent r="7" t="21" w="2426" /><ent r="7" t="21" w="3679" /><ent r="7" t="21" w="3679" /><ent r="7" t="21" w="3820" /><ent r="7" t="21" w="3820" /><ent r="7" t="21" w="3828" /><ent r="7" t="21" w="3828" /><ent r="7" t="21" w="4369" /><ent r="7" t="21" w="4369" /><ent r="8" t="21" w="4646" /><ent r="7" t="25" w="1682" /><ent r="7" t="25" w="3178" /><ent r="7" t="25" w="3178" /><ent r="7" t="25" w="3251" /><ent r="7" t="25" w="3251" /><ent r="7" t="25" w="3257" /><ent r="7" t="25" w="3257" /><ent r="7" t="25" w="3284" /><ent r="7" t="25" w="3284" /><ent r="7" t="25" w="3931" /><ent r="7" t="25" w="4189" /><ent r="7" t="25" w="4878" /><ent r="7" t="25" w="4878" /><ent r="7" t="25" w="5185" /><ent r="7" t="25" w="5185" /></phr></stem><stem n="statu"><phr n="status"><ent r="8" t="8" w="6628" /><ent r="8" t="8" w="6628" /><ent r="8" t="8" w="6673" /><ent r="8" t="8" w="6673" /><ent r="7" t="10" w="1828" /><ent r="7" t="10" w="1828" /><ent r="7" t="13" w="1428" /><ent r="7" t="13" w="1428" /><ent r="8" t="13" w="3475" /><ent r="8" t="13" w="3475" /><ent r="8" t="13" w="5824" /><ent r="8" t="13" w="6082" /><ent r="8" t="13" w="6082" /><ent r="8" t="13" w="10823" /><ent r="8" t="13" w="10823" /><ent r="8" t="13" w="10936" /><ent r="8" t="13" w="10936" /><ent r="8" t="14" w="5467" /><ent r="8" t="14" w="5467" /><ent r="8" t="14" w="5483" /><ent r="8" t="14" w="5500" /><ent r="8" t="14" w="5500" /><ent r="8" t="14" w="5517" /><ent r="8" t="14" w="5517" /><ent r="8" t="14" w="5542" /><ent r="8" t="14" w="5542" /><ent r="7" t="25" w="2640" /></phr><phr n="STATUS"><ent r="8" t="13" w="6065" /><ent r="8" t="13" w="6065" /></phr><phr n="Status"><ent r="8" t="13" w="10796" /><ent r="8" t="13" w="10796" /><ent r="7" t="13" w="10863" /><ent r="7" t="13" w="10863" /><ent r="8" t="13" w="10916" /><ent r="8" t="13" w="10916" /><ent r="9" t="13" w="10939" /><ent r="9" t="13" w="10939" /><ent r="9" t="13" w="10960" /><ent r="9" t="13" w="10960" /><ent r="9" t="13" w="10998" /><ent r="9" t="13" w="10998" /></phr></stem><stem n="combin"><phr n="combined"><ent r="7" t="8" w="6706" /><ent r="7" t="8" w="6706" /><ent r="8" t="12" w="9153" /><ent r="8" t="12" w="9153" /><ent r="7" t="16" w="4681" /><ent r="7" t="16" w="4681" /><ent r="7" t="16" w="4761" /><ent r="7" t="16" w="4761" /><ent r="7" t="16" w="4954" /><ent r="7" t="16" w="4954" /><ent r="7" t="16" w="7550" /><ent r="7" t="16" w="7550" /><ent r="7" t="18" w="9033" /><ent r="7" t="18" w="9033" /></phr><phr n="combining"><ent r="7" t="8" w="7828" /><ent r="7" t="8" w="7828" /><ent r="8" t="12" w="11205" /><ent r="8" t="12" w="11205" /></phr><phr n="combination"><ent r="7" t="8" w="9134" /><ent r="7" t="8" w="9134" /><ent r="7" t="12" w="11552" /><ent r="7" t="12" w="11552" /><ent r="7" t="13" w="2045" /><ent r="7" t="13" w="2045" /><ent r="7" t="14" w="6783" /><ent r="7" t="14" w="6783" /><ent r="7" t="18" w="7215" /><ent r="7" t="18" w="7215" /><ent r="7" t="20" w="1181" /><ent r="7" t="20" w="1181" /><ent r="7" t="25" w="2823" /><ent r="7" t="25" w="2823" /></phr><phr n="combinations"><ent r="8" t="12" w="9539" /><ent r="8" t="12" w="9539" /><ent r="8" t="14" w="6755" /><ent r="8" t="14" w="6755" /><ent r="8" t="20" w="5082" /><ent r="8" t="20" w="5082" /></phr><phr n="Combinations"><ent r="7" t="14" w="4580" /><ent r="7" t="14" w="4580" /><ent r="77" t="14" w="6728" /><ent r="77" t="14" w="6728" /></phr><phr n="Combine"><ent r="7" t="16" w="4424" /><ent r="7" t="16" w="4424" /></phr><phr n="combine"><ent r="7" t="16" w="5634" /><ent r="7" t="16" w="5634" /><ent r="7" t="21" w="2812" /><ent r="7" t="21" w="2812" /><ent r="7" t="21" w="4799" /><ent r="7" t="21" w="4799" /></phr><phr n="combines"><ent r="7" t="25" w="1713" /><ent r="7" t="25" w="1713" /></phr></stem><stem n="imper"><phr n="imperative"><ent r="7" t="8" w="6743" /><ent r="7" t="8" w="6743" /><ent r="7" t="8" w="6837" /><ent r="7" t="8" w="6837" /><ent r="7" t="8" w="6856" /><ent r="7" t="8" w="6856" /><ent r="7" t="8" w="6931" /><ent r="7" t="8" w="6931" /><ent r="7" t="8" w="6999" /><ent r="7" t="8" w="6999" /><ent r="7" t="8" w="7010" /><ent r="7" t="8" w="7010" /><ent r="7" t="8" w="7048" /><ent r="7" t="8" w="7088" /><ent r="7" t="8" w="7088" /><ent r="7" t="8" w="7111" /><ent r="7" t="8" w="7111" /><ent r="7" t="8" w="7197" /><ent r="7" t="8" w="7197" /><ent r="7" t="14" w="2852" /><ent r="7" t="14" w="2852" /><ent r="8" t="25" w="2082" /><ent r="8" t="25" w="2082" /></phr><phr n="imperatives"><ent r="7" t="13" w="8401" /><ent r="7" t="13" w="8401" /></phr><phr n="Imperative"><ent r="7" t="20" w="2422" /><ent r="7" t="20" w="2422" /></phr></stem><stem n="pick"><phr n="pick"><ent r="7" t="8" w="6772" /><ent r="7" t="8" w="6772" /><ent r="7" t="10" w="5083" /><ent r="7" t="10" w="5083" /><ent r="7" t="10" w="9502" /><ent r="7" t="10" w="9502" /><ent r="8" t="12" w="10418" /><ent r="8" t="12" w="10418" /><ent r="7" t="16" w="11398" /><ent r="7" t="16" w="11398" /><ent r="7" t="21" w="3642" /><ent r="7" t="21" w="3642" /><ent r="7" t="21" w="5385" /><ent r="7" t="21" w="5385" /></phr><phr n="picked"><ent r="7" t="9" w="4634" /><ent r="7" t="9" w="4634" /></phr><phr n="Pick"><ent r="7" t="25" w="1815" /><ent r="7" t="25" w="1815" /></phr></stem><stem n="altern"><phr n="alternative"><ent r="7" t="8" w="6810" /><ent r="7" t="8" w="6810" /><ent r="7" t="10" w="6015" /><ent r="7" t="10" w="6015" /><ent r="8" t="18" w="9984" /><ent r="8" t="18" w="9984" /><ent r="7" t="18" w="10005" /><ent r="7" t="18" w="10005" /><ent r="7" t="18" w="10061" /><ent r="7" t="18" w="10061" /><ent r="7" t="18" w="10113" /><ent r="7" t="18" w="10113" /><ent r="7" t="18" w="10142" /><ent r="7" t="18" w="10142" /><ent r="7" t="18" w="10196" /><ent r="7" t="18" w="10196" /><ent r="7" t="18" w="10231" /><ent r="7" t="18" w="10231" /><ent r="7" t="21" w="1489" /><ent r="7" t="21" w="1489" /><ent r="7" t="21" w="4595" /><ent r="7" t="21" w="4595" /><ent r="8" t="25" w="291" /><ent r="8" t="25" w="291" /><ent r="7" t="25" w="314" /><ent r="7" t="25" w="314" /></phr><phr n="alternatives"><ent r="7" t="12" w="6979" /><ent r="7" t="13" w="11264" /><ent r="8" t="13" w="11276" /><ent r="8" t="13" w="11276" /><ent r="7" t="18" w="9679" /></phr><phr n="Alternative"><ent r="7" t="13" w="9599" /><ent r="7" t="13" w="9599" /><ent r="77" t="18" w="9923" /><ent r="77" t="18" w="9923" /><ent r="8" t="18" w="10019" /><ent r="8" t="18" w="10019" /><ent r="7" t="25" w="327" /><ent r="7" t="25" w="327" /></phr><phr n="Alternatively"><ent r="7" t="17" w="6674" /><ent r="7" t="17" w="7699" /><ent r="7" t="18" w="4154" /></phr><phr n="alternate"><ent r="7" t="18" w="8903" /><ent r="7" t="18" w="8903" /><ent r="7" t="18" w="10048" /><ent r="7" t="18" w="10048" /><ent r="7" t="21" w="6249" /><ent r="7" t="21" w="6249" /></phr></stem><stem n="trickier"><phr n="trickier"><ent r="7" t="8" w="6850" /><ent r="7" t="8" w="6850" /></phr></stem><stem n="infoverifi"><phr n="InfoVerify"><ent r="8" t="8" w="6910" /><ent r="8" t="8" w="6910" /><ent r="8" t="8" w="6985" /><ent r="8" t="8" w="6985" /></phr></stem><stem n="virus"><phr n="viruses"><ent r="8" t="8" w="6915" /><ent r="8" t="8" w="6990" /></phr></stem><stem n="break"><phr n="breaks"><ent r="7" t="8" w="6925" /><ent r="7" t="8" w="6925" /></phr><phr n="break"><ent r="7" t="10" w="8357" /><ent r="7" t="10" w="8357" /><ent r="7" t="12" w="283" /><ent r="7" t="12" w="283" /><ent r="7" t="18" w="9027" /><ent r="7" t="18" w="9027" /><ent r="7" t="18" w="9252" /><ent r="7" t="18" w="9252" /></phr><phr n="Break"><ent r="7" t="17" w="7921" /><ent r="7" t="17" w="7921" /></phr></stem><stem n="convei"><phr n="conveys"><ent r="7" t="8" w="7015" /><ent r="7" t="8" w="7015" /><ent r="8" t="12" w="3158" /><ent r="8" t="12" w="3158" /><ent r="8" t="12" w="5870" /><ent r="8" t="12" w="5870" /><ent r="8" t="14" w="1386" /><ent r="8" t="14" w="1386" /><ent r="7" t="14" w="2173" /><ent r="7" t="14" w="2173" /><ent r="7" t="18" w="2674" /><ent r="7" t="18" w="2674" /><ent r="7" t="18" w="2798" /><ent r="7" t="18" w="2798" /><ent r="7" t="18" w="2810" /><ent r="7" t="18" w="2810" /><ent r="7" t="18" w="6330" /><ent r="7" t="18" w="6330" /><ent r="7" t="18" w="10210" /><ent r="7" t="20" w="5446" /><ent r="7" t="20" w="5446" /><ent r="7" t="25" w="303" /><ent r="7" t="25" w="303" /><ent r="7" t="25" w="4992" /><ent r="7" t="25" w="4992" /></phr><phr n="Convey"><ent r="68" t="11" w="381" /><ent r="68" t="11" w="381" /><ent r="68" t="13" w="11179" /><ent r="68" t="13" w="11179" /><ent r="69" t="14" w="429" /><ent r="69" t="14" w="429" /><ent r="87" t="14" w="1380" /><ent r="87" t="14" w="1380" /><ent r="68" t="27" w="665" /><ent r="68" t="27" w="665" /></phr><phr n="convey"><ent r="7" t="12" w="323" /><ent r="7" t="12" w="323" /><ent r="8" t="12" w="502" /><ent r="7" t="12" w="3883" /><ent r="7" t="12" w="3925" /><ent r="8" t="12" w="5898" /><ent r="8" t="12" w="5898" /><ent r="8" t="12" w="6418" /><ent r="8" t="12" w="6418" /><ent r="7" t="12" w="7091" /><ent r="7" t="14" w="2266" /><ent r="7" t="14" w="2266" /><ent r="7" t="16" w="1255" /><ent r="7" t="16" w="1255" /><ent r="7" t="16" w="8469" /><ent r="7" t="16" w="8469" /><ent r="7" t="16" w="8548" /><ent r="7" t="16" w="8548" /><ent r="7" t="17" w="990" /><ent r="7" t="17" w="990" /><ent r="7" t="17" w="8120" /><ent r="7" t="17" w="8120" /><ent r="8" t="18" w="830" /><ent r="8" t="18" w="830" /><ent r="7" t="18" w="1458" /><ent r="8" t="18" w="1912" /><ent r="8" t="18" w="1912" /><ent r="7" t="18" w="2096" /><ent r="7" t="18" w="2096" /><ent r="8" t="18" w="2609" /><ent r="8" t="18" w="2609" /><ent r="7" t="18" w="3786" /><ent r="7" t="18" w="3786" /><ent r="7" t="18" w="4157" /><ent r="7" t="18" w="4157" /><ent r="7" t="18" w="4353" /><ent r="7" t="18" w="4353" /><ent r="7" t="18" w="7141" /><ent r="7" t="18" w="7141" /><ent r="7" t="18" w="7274" /><ent r="7" t="18" w="7274" /><ent r="8" t="18" w="10248" /><ent r="8" t="18" w="10248" /><ent r="7" t="18" w="10599" /><ent r="7" t="18" w="10599" /><ent r="8" t="21" w="5660" /><ent r="8" t="21" w="5660" /></phr><phr n="conveyed"><ent r="7" t="14" w="1604" /><ent r="7" t="14" w="1604" /><ent r="7" t="18" w="1430" /><ent r="7" t="18" w="1430" /><ent r="8" t="18" w="9970" /><ent r="8" t="18" w="9970" /></phr><phr n="conveying"><ent r="7" t="17" w="7957" /><ent r="8" t="18" w="2721" /><ent r="8" t="18" w="2721" /></phr><phr n="Conveyed"><ent r="7" t="18" w="4111" /><ent r="7" t="18" w="4111" /></phr></stem><stem n="port"><phr n="port"><ent r="8" t="8" w="7158" /><ent r="8" t="8" w="7158" /><ent r="8" t="8" w="7256" /><ent r="8" t="8" w="7256" /><ent r="8" t="10" w="1202" /></phr><phr n="Port"><ent r="8" t="14" w="7980" /><ent r="8" t="14" w="7980" /><ent r="8" t="14" w="8076" /><ent r="8" t="14" w="8076" /><ent r="8" t="14" w="8237" /><ent r="8" t="14" w="8237" /></phr></stem><stem n="60000"><phr n="60000"><ent r="8" t="8" w="7161" /><ent r="8" t="8" w="7161" /><ent r="8" t="8" w="7259" /><ent r="8" t="8" w="7259" /></phr></stem><stem n="65000"><phr n="65000"><ent r="8" t="8" w="7163" /><ent r="8" t="8" w="7261" /></phr></stem><stem n="mind-numbingli"><phr n="mind-numbingly"><ent r="8" t="8" w="7333" /><ent r="8" t="8" w="7333" /></phr></stem><stem n="numbingli"><phr n="numbingly"><ent r="8" t="8" w="7334" /></phr></stem><stem n="obscur"><phr n="obscure"><ent r="8" t="8" w="7335" /><ent r="8" t="12" w="1207" /><ent r="8" t="12" w="1207" /><ent r="7" t="12" w="3390" /><ent r="7" t="12" w="3390" /></phr><phr n="obscured"><ent r="7" t="10" w="9710" /><ent r="7" t="10" w="9710" /><ent r="7" t="12" w="1426" /><ent r="7" t="12" w="1426" /></phr><phr n="obscures"><ent r="7" t="20" w="4573" /><ent r="7" t="20" w="4573" /></phr><phr n="obscurity"><ent r="7" t="25" w="605" /></phr></stem><stem n="larger"><phr n="larger"><ent r="8" t="8" w="7345" /><ent r="8" t="8" w="7345" /><ent r="7" t="13" w="7541" /><ent r="7" t="13" w="7541" /><ent r="7" t="13" w="10781" /><ent r="7" t="13" w="10781" /><ent r="8" t="16" w="268" /><ent r="8" t="16" w="268" /><ent r="7" t="16" w="1202" /><ent r="7" t="16" w="1202" /><ent r="7" t="16" w="4429" /><ent r="7" t="16" w="4429" /><ent r="7" t="16" w="10314" /><ent r="7" t="16" w="10314" /><ent r="7" t="18" w="1549" /><ent r="7" t="18" w="1549" /><ent r="7" t="18" w="6709" /><ent r="7" t="18" w="6709" /><ent r="7" t="18" w="6714" /><ent r="7" t="18" w="6714" /><ent r="7" t="18" w="6801" /><ent r="7" t="18" w="6801" /><ent r="7" t="18" w="8464" /><ent r="7" t="18" w="8464" /><ent r="8" t="18" w="9639" /><ent r="8" t="18" w="9639" /><ent r="7" t="20" w="5220" /><ent r="7" t="20" w="5220" /><ent r="7" t="25" w="2484" /><ent r="7" t="25" w="2484" /><ent r="7" t="25" w="4679" /><ent r="7" t="25" w="4679" /></phr></stem><stem n="interpret"><phr n="interpreting"><ent r="7" t="8" w="7367" /><ent r="7" t="8" w="7367" /></phr><phr n="interpret"><ent r="7" t="12" w="201" /><ent r="7" t="12" w="201" /><ent r="8" t="14" w="1432" /><ent r="8" t="14" w="1432" /><ent r="7" t="14" w="2518" /><ent r="7" t="14" w="2518" /><ent r="7" t="14" w="5570" /><ent r="7" t="14" w="5570" /></phr><phr n="interpretation"><ent r="7" t="12" w="5602" /><ent r="7" t="12" w="5602" /></phr><phr n="interpretations"><ent r="7" t="14" w="2477" /><ent r="7" t="14" w="2477" /></phr></stem><stem n="fill"><phr n="fill"><ent r="7" t="8" w="7377" /><ent r="7" t="8" w="7377" /><ent r="7" t="8" w="8067" /><ent r="7" t="8" w="8067" /><ent r="7" t="10" w="9528" /><ent r="7" t="10" w="9528" /><ent r="7" t="10" w="9643" /><ent r="7" t="10" w="9643" /><ent r="8" t="16" w="2725" /><ent r="8" t="16" w="2725" /><ent r="7" t="16" w="2990" /><ent r="7" t="16" w="2990" /><ent r="7" t="18" w="8323" /><ent r="7" t="18" w="8323" /></phr><phr n="filled"><ent r="7" t="20" w="5424" /><ent r="7" t="20" w="5424" /></phr><phr n="Fill"><ent r="7" t="21" w="6066" /><ent r="7" t="21" w="6066" /></phr><phr n="filling"><ent r="7" t="25" w="2593" /><ent r="7" t="25" w="2593" /><ent r="7" t="25" w="5543" /><ent r="7" t="25" w="5543" /></phr></stem><stem n="grasp"><phr n="grasp"><ent r="7" t="8" w="7399" /><ent r="7" t="8" w="7399" /><ent r="7" t="12" w="7139" /><ent r="7" t="12" w="7139" /><ent r="7" t="16" w="8947" /><ent r="7" t="16" w="8947" /><ent r="7" t="16" w="9855" /><ent r="7" t="16" w="9855" /><ent r="7" t="17" w="3367" /><ent r="7" t="17" w="3367" /><ent r="7" t="18" w="6365" /><ent r="7" t="18" w="6365" /><ent r="7" t="20" w="4738" /></phr></stem><stem n="my"><phr n="my"><ent r="7" t="8" w="7408" /><ent r="7" t="8" w="7408" /></phr><phr n="My"><ent r="8" t="10" w="9018" /><ent r="8" t="10" w="9018" /><ent r="8" t="10" w="9170" /><ent r="8" t="10" w="9170" /><ent r="4" t="37" w="3" /><ent r="4" t="37" w="3" /></phr></stem><stem n="properti"><phr n="Properties"><ent r="9" t="8" w="7499" /><ent r="9" t="8" w="7499" /><ent r="8" t="8" w="7509" /><ent r="8" t="8" w="7509" /><ent r="8" t="8" w="7525" /><ent r="8" t="8" w="7525" /><ent r="9" t="8" w="7661" /><ent r="9" t="8" w="7661" /><ent r="8" t="8" w="7671" /><ent r="8" t="8" w="7671" /><ent r="9" t="12" w="4052" /><ent r="9" t="12" w="4052" /><ent r="9" t="12" w="4189" /><ent r="9" t="12" w="4189" /><ent r="10" t="12" w="4552" /><ent r="10" t="12" w="4552" /><ent r="7" t="12" w="4652" /><ent r="7" t="12" w="4652" /><ent r="10" t="12" w="4884" /><ent r="10" t="12" w="4884" /></phr><phr n="property"><ent r="8" t="9" w="4616" /><ent r="8" t="9" w="4692" /><ent r="8" t="9" w="4692" /><ent r="8" t="12" w="4515" /><ent r="8" t="12" w="4515" /><ent r="7" t="14" w="3692" /><ent r="7" t="14" w="3692" /><ent r="7" t="17" w="5582" /><ent r="7" t="17" w="5582" /></phr><phr n="properties"><ent r="7" t="12" w="4618" /><ent r="8" t="12" w="4877" /><ent r="8" t="12" w="4877" /><ent r="7" t="12" w="5062" /><ent r="7" t="12" w="5069" /><ent r="7" t="12" w="5085" /><ent r="9" t="12" w="9528" /><ent r="9" t="12" w="9528" /><ent r="8" t="12" w="10650" /><ent r="8" t="12" w="10650" /><ent r="8" t="12" w="10672" /><ent r="8" t="12" w="10672" /><ent r="8" t="12" w="10717" /><ent r="8" t="12" w="10717" /><ent r="8" t="12" w="10740" /><ent r="8" t="12" w="10740" /><ent r="7" t="16" w="2292" /><ent r="7" t="16" w="2292" /><ent r="7" t="16" w="2308" /><ent r="7" t="16" w="2308" /><ent r="7" t="16" w="2327" /><ent r="7" t="16" w="2327" /><ent r="7" t="16" w="2339" /><ent r="7" t="16" w="2339" /><ent r="7" t="16" w="2386" /><ent r="7" t="16" w="2386" /><ent r="7" t="21" w="694" /><ent r="7" t="21" w="694" /></phr></stem><stem n="-file"><phr n="-file"><ent r="9" t="8" w="7568" /><ent r="9" t="8" w="7726" /></phr></stem><stem n="yourprofilenam"><phr n="yourProfileName"><ent r="10" t="8" w="7570" /><ent r="10" t="8" w="7570" /><ent r="10" t="8" w="7728" /><ent r="10" t="8" w="7728" /></phr></stem><stem n="browser"><phr n="browser"><ent r="8" t="8" w="7579" /><ent r="8" t="8" w="7737" /><ent r="7" t="10" w="1524" /><ent r="7" t="10" w="2031" /><ent r="7" t="10" w="2031" /><ent r="8" t="10" w="7872" /><ent r="8" t="10" w="7872" /><ent r="8" t="10" w="7878" /><ent r="8" t="10" w="7878" /><ent r="8" t="10" w="8095" /><ent r="8" t="10" w="8095" /><ent r="8" t="13" w="4724" /><ent r="8" t="13" w="4724" /><ent r="8" t="13" w="4883" /><ent r="8" t="13" w="4883" /><ent r="8" t="16" w="2643" /><ent r="8" t="16" w="2706" /><ent r="8" t="16" w="3099" /><ent r="8" t="16" w="3162" /><ent r="7" t="17" w="7915" /><ent r="7" t="17" w="7915" /><ent r="7" t="18" w="6923" /><ent r="7" t="18" w="9853" /><ent r="7" t="18" w="9853" /></phr><phr n="browsers"><ent r="7" t="10" w="5071" /><ent r="7" t="10" w="5071" /><ent r="7" t="17" w="2908" /><ent r="7" t="17" w="2908" /><ent r="7" t="17" w="3028" /><ent r="7" t="21" w="2292" /></phr><phr n="Browser"><ent r="8" t="10" w="7905" /><ent r="8" t="10" w="7905" /><ent r="8" t="10" w="8101" /><ent r="8" t="10" w="8101" /></phr></stem><stem n="weight"><phr n="weight"><ent r="7" t="8" w="7591" /><ent r="7" t="12" w="3938" /><ent r="8" t="13" w="4499" /><ent r="8" t="13" w="4499" /><ent r="7" t="18" w="7469" /><ent r="7" t="25" w="4000" /></phr><phr n="weighting"><ent r="8" t="17" w="7130" /><ent r="8" t="17" w="7130" /></phr><phr n="weights"><ent r="7" t="18" w="7134" /><ent r="7" t="18" w="7134" /><ent r="7" t="18" w="7204" /><ent r="7" t="18" w="7204" /><ent r="7" t="18" w="7281" /><ent r="7" t="18" w="7281" /><ent r="7" t="18" w="7644" /><ent r="7" t="18" w="7830" /></phr></stem><stem n="treat"><phr n="treated"><ent r="7" t="8" w="7600" /><ent r="7" t="8" w="7600" /><ent r="7" t="10" w="3430" /><ent r="7" t="10" w="3430" /><ent r="8" t="12" w="858" /><ent r="8" t="12" w="858" /><ent r="8" t="12" w="925" /><ent r="8" t="12" w="925" /><ent r="8" t="12" w="5652" /><ent r="8" t="12" w="5652" /><ent r="7" t="20" w="4377" /><ent r="7" t="20" w="4377" /><ent r="7" t="21" w="3500" /><ent r="7" t="21" w="3500" /></phr><phr n="treats"><ent r="7" t="16" w="10385" /><ent r="7" t="16" w="10385" /></phr></stem><stem n="relationship"><phr n="relationship"><ent r="7" t="8" w="7623" /><ent r="7" t="8" w="7623" /><ent r="7" t="9" w="2946" /><ent r="7" t="9" w="2946" /><ent r="7" t="12" w="5079" /><ent r="7" t="12" w="5079" /><ent r="7" t="12" w="5092" /><ent r="7" t="12" w="5092" /><ent r="7" t="13" w="8380" /><ent r="7" t="13" w="8380" /><ent r="7" t="13" w="10782" /><ent r="7" t="14" w="5927" /><ent r="7" t="14" w="5927" /><ent r="7" t="14" w="5948" /><ent r="7" t="14" w="5948" /><ent r="7" t="16" w="8759" /><ent r="7" t="16" w="8759" /><ent r="8" t="17" w="8495" /><ent r="8" t="17" w="8495" /><ent r="8" t="17" w="8500" /><ent r="8" t="17" w="8500" /><ent r="8" t="17" w="8508" /><ent r="8" t="17" w="8514" /><ent r="8" t="17" w="8514" /><ent r="8" t="17" w="8522" /><ent r="8" t="17" w="8526" /><ent r="8" t="17" w="8526" /><ent r="8" t="17" w="8553" /><ent r="8" t="17" w="8553" /><ent r="8" t="17" w="8585" /><ent r="8" t="17" w="8585" /><ent r="8" t="17" w="8634" /><ent r="8" t="17" w="8634" /><ent r="8" t="17" w="8645" /><ent r="8" t="17" w="8657" /><ent r="8" t="17" w="8708" /><ent r="8" t="17" w="8708" /><ent r="7" t="18" w="10656" /><ent r="7" t="18" w="10656" /><ent r="7" t="20" w="3073" /><ent r="7" t="20" w="3073" /></phr><phr n="relationships"><ent r="7" t="8" w="7746" /><ent r="7" t="8" w="7746" /><ent r="7" t="12" w="199" /><ent r="8" t="12" w="637" /><ent r="8" t="12" w="637" /><ent r="8" t="12" w="6421" /><ent r="8" t="12" w="6421" /><ent r="7" t="13" w="1279" /><ent r="7" t="13" w="5003" /><ent r="7" t="13" w="5003" /><ent r="8" t="13" w="10616" /><ent r="8" t="13" w="10682" /><ent r="7" t="16" w="5533" /><ent r="7" t="16" w="5533" /><ent r="7" t="16" w="5730" /><ent r="7" t="16" w="5797" /><ent r="7" t="16" w="5797" /><ent r="8" t="16" w="5884" /><ent r="7" t="16" w="5903" /><ent r="7" t="16" w="8391" /><ent r="7" t="16" w="8471" /><ent r="7" t="16" w="8471" /><ent r="7" t="16" w="8874" /><ent r="7" t="16" w="8874" /><ent r="7" t="16" w="8943" /><ent r="7" t="16" w="8943" /><ent r="7" t="16" w="9350" /><ent r="7" t="16" w="10363" /><ent r="7" t="16" w="10363" /><ent r="7" t="16" w="10397" /><ent r="7" t="16" w="10397" /><ent r="7" t="18" w="542" /><ent r="7" t="18" w="542" /><ent r="8" t="18" w="1918" /><ent r="8" t="18" w="2286" /><ent r="8" t="18" w="2461" /><ent r="67" t="18" w="2600" /><ent r="67" t="18" w="2600" /><ent r="8" t="18" w="2640" /><ent r="8" t="18" w="2729" /><ent r="7" t="18" w="7359" /><ent r="7" t="18" w="7374" /><ent r="7" t="18" w="7374" /><ent r="7" t="18" w="7413" /><ent r="8" t="18" w="8687" /><ent r="8" t="18" w="8687" /><ent r="7" t="21" w="4173" /><ent r="7" t="21" w="4173" /><ent r="7" t="25" w="764" /></phr><phr n="Relationship"><ent r="8" t="12" w="4925" /><ent r="8" t="12" w="4925" /><ent r="7" t="12" w="4931" /><ent r="7" t="12" w="4931" /></phr></stem></index>